backtestsuite/__init__.py
backtestsuite/analysis/__init__.py
backtestsuite/analysis/bt_analysis.py
backtestsuite/config/__init__.py
backtestsuite/core/__init__.py
backtestsuite/core/btcore.py
backtestsuite/playground/__init__.py
backtestsuite/playground/backtest_bt.py
backtestsuite/playground/backtest_vn.py
backtestsuite/playground/load_html.py
backtestsuite/quote/__init__.py
backtestsuite/quote/akshare_quote.py
backtestsuite-0.0.2.dist-info/LICENSE
backtestsuite-0.0.2.dist-info/METADATA
backtestsuite-0.0.2.dist-info/WHEEL
backtestsuite-0.0.2.dist-info/top_level.txt
backtestsuite-0.0.2.dist-info/RECORD
