Metadata-Version: 2.1
Name: backtestsuite
Version: 0.0.2
Summary: backtest
Home-page: 
Author: sn0wfree
Author-email: snowfreedom0815@gmail.com
License: MIT Licence
Keywords: backtestsuite,backtest,Analysis
License-File: LICENSE
